upadup/__init__.py
upadup/config.py
upadup/dep_parser.py
upadup/main.py
upadup/package_utils.py
upadup/updater.py
upadup/yaml.py
upadup-0.3.1.dist-info/entry_points.txt
upadup-0.3.1.dist-info/WHEEL
upadup-0.3.1.dist-info/METADATA
upadup-0.3.1.dist-info/RECORD
