Metadata-Version: 2.3
Name: upadup
Version: 0.3.1
Summary: utility for python additional_dependencies updates in pre-commit
Keywords: 
Author-email: Stephen Rosen <sirosen0@gmail.com>
Requires-Python: >=3.9
Classifier: Development Status :: 4 - Beta
Classifier: Programming Language :: Python
Classifier: Programming Language :: Python :: 3.9
Classifier: Programming Language :: Python :: 3.10
Classifier: Programming Language :: Python :: 3.11
Classifier: Programming Language :: Python :: 3.12
Classifier: Programming Language :: Python :: 3.13
Classifier: Programming Language :: Python :: Implementation :: CPython
Classifier: Programming Language :: Python :: Implementation :: PyPy
Requires-Dist: requests>=2,<3
Requires-Dist: ruamel.yaml>=0.18.10,<0.19
Project-URL: documentation, https://github.com/sirosen/upadup#readme
Project-URL: issues, https://github.com/sirosen/upadup/issues
Project-URL: source, https://github.com/sirosen/upadup
